Workbook

Sheet Sales Register
A1: Shree Ganesh Traders — Sales Register, September 2026
A2: GSTIN 24AAQFS8812K1Z4 · Edited by Ravi · Sample demo data (fictional)
A4: Invoice No | B4: Invoice Date | C4: Customer Name | D4: Customer GSTIN | E4: Item | F4: HSN | G4: Qty | H4: Rate (₹) | I4: Taxable Value (₹) | J4: GST % | K4: GST Amount (₹) | L4: Invoice Total (₹)
A5: INV-1001 | B5: 46266 | C5: Joshi Enterprises | D5: 24AFJPJ1188B1Z2 | E5: Jute Sacks (bundle of 50) | F5: 6305 | G5: 40 | H5: 1250 | I5: =G5*H5 -> 50000 | J5: 0.05 | K5: =I5*J5 -> 2500 | L5: =I5+K5 -> 52500
A6: INV-1002 | B6: 46267 | C6: Bhatt & Sons | D6: 24AAGFB2267C1Z1 | E6: Modular Switch 6A | F6: 8536 | G6: 150 | H6: 38 | I6: =G6*H6 -> 5700 | J6: 0.18 | K6: =I6*J6 -> 1026 | L6: =I6+K6 -> 6726
A7: INV-1003 | B7: 46268 | C7: Shah Electricals | D7: 24ABCPS7712Q1ZK | E7: Copper Wire 1.5 sq mm (coil) | F7: 8544 | G7: 30 | H7: 1890 | I7: =G7*H7 -> 56700 | J7: 0.18 | K7: =I7*J7 -> 10206 | L7: =I7+K7 -> 66906
A8: INV-1004 | B8: 46269 | C8: Desai Traders | D8: 24AAMFD6041L1Z7 | E8: Door Hinges 4in (pair) | F8: 8302 | G8: 8 | H8: 145 | I8: =G8*H8 -> 1160 | J8: 0.18 | K8: =I8*J8 -> 208.8 | L8: =I8+K8 -> 1368.8
A9: INV-1005 | B9: 46270 | C9: Trivedi Infra Projects | D9: 24AAHCT9034R1Z6 | E9: Exterior Emulsion 20L | F9: 3208 | G9: 60 | H9: 5650 | I9: =G9*H9 -> 339000 | J9: 0.18 | K9: =I9*J9 -> 61020 | L9: =I9+K9 -> 400020
A10: INV-1006 | B10: 46271 | C10: Mehta Building Supplies | D10: 24AADFM3390H1Z9 | E10: Wall Putty 40kg | F10: 3214 | G10: 35 | H10: 780 | I10: =G10*H10 -> 27300 | J10: 0.18 | K10: =I10*J10 -> 4914 | L10: =I10+K10 -> 32214
A11: INV-1007 | B11: 46272 | C11: Rathod Paints & Hardware | D11: 24ACQPR5529N1ZB | E11: PVC Conduit Pipe 25mm | F11: 3917 | G11: 18 | H11: 96 | I11: =G11*H11 -> 1728 | J11: 0.18 | K11: =I11*J11 -> 311.04 | L11: =I11+K11 -> 2039.04
A12: INV-1008 | B12: 46273 | C12: Patel Hardware Stores | D12: 24AAKFP4521M1Z3 | E12: SS Screws 50mm (box) | F12: 7318 | G12: 45 | H12: 420 | I12: =G12*H12 -> 18900 | J12: 0.18 | K12: =I12*J12 -> 3402 | L12: =I12+K12 -> 22302
A13: INV-1009 | B13: 46274 | C13: Joshi Enterprises | D13: 24AFJPJ1188B1Z2 | E13: Jute Sacks (bundle of 50) | F13: 6305 | G13: 22 | H13: 1250 | I13: =G13*H13 -> 27500 | J13: 0.05 | K13: =I13*J13 -> 1375 | L13: =I13+K13 -> 28875
A14: INV-1010 | B14: 46275 | C14: Bhatt & Sons | D14: 24AAGFB2267C1Z1 | E14: Modular Switch 6A | F14: 8536 | G14: 12 | H14: 38 | I14: =G14*H14 -> 456 | J14: 0.18 | K14: =I14*J14 -> 82.08 | L14: =I14+K14 -> 538.08
A15: INV-1011 | B15: 46276 | C15: Shah Electricals | D15: 24ABCPS7712Q1ZK | E15: Copper Wire 1.5 sq mm (coil) | F15: 8544 | G15: 40 | H15: 1890 | I15: =G15*H15 -> 75600 | J15: 0.18 | K15: =I15*J15 -> 13608 | L15: =I15+K15 -> 89208
A16: INV-1012 | B16: 46277 | C16: Desai Traders | D16: 24AAMFD6041L1Z7 | E16: Door Hinges 4in (pair) | F16: 8302 | G16: 150 | H16: 145 | I16: =G16*H16 -> 21750 | J16: 0.18 | K16: =I16*J16 -> 3915 | L16: =I16+K16 -> 25665
... A32: INV-1030 | B32: 46295 | C32: Mehta Building Supplies | D32: 24AADFM3390H1Z9 | E32: Wall Putty 40kg | F32: 3214 | G32: 12 | H32: 780 | I32: =G32*H32 -> 9360 | J32: 0.18 | K32: =I32*J32 -> 1684.8 | L32: =I32+K32 -> 11044.8

Sheet Summary
A1: GSTR-1 Summary — September 2026
A3: Particulars | B3: Amount
A4: Number of invoices | B4: =COUNTA('Sales Register'!A5:A32) -> 28
A5: Total taxable value (₹) | B5: =SUM('Sales Register'!I5:I32) -> 1286674
A6: Taxable value @ 5% (₹) | B6: =SUMIF('Sales Register'!J5:J32,0.05,'Sales Register'!I5:I32) -> 292000
A7: Taxable value @ 18% (₹) | B7: =SUMIF('Sales Register'!J5:J32,0.18,'Sales Register'!I5:I32) -> 994674
A8: Total GST payable (₹) | B8: =SUM('Sales Register'!K5:K32) -> 193641.32
A9: Total invoice value (₹) | B9: =SUM('Sales Register'!L5:L32) -> 1480315.3
